data_juicer/__init__.py
data_juicer/analysis/__init__.py
data_juicer/analysis/collector.py
data_juicer/analysis/column_wise_analysis.py
data_juicer/analysis/correlation_analysis.py
data_juicer/analysis/diversity_analysis.py
data_juicer/analysis/measure.py
data_juicer/analysis/overall_analysis.py
data_juicer/config/__init__.py
data_juicer/config/config.py
data_juicer/config/config_all.yaml
data_juicer/config/config_min.yaml
data_juicer/core/__init__.py
data_juicer/core/adapter.py
data_juicer/core/analyzer.py
data_juicer/core/exporter.py
data_juicer/core/monitor.py
data_juicer/core/ray_exporter.py
data_juicer/core/tracer.py
data_juicer/core/data/__init__.py
data_juicer/core/data/config_validator.py
data_juicer/core/data/data_validator.py
data_juicer/core/data/dataset_builder.py
data_juicer/core/data/dj_dataset.py
data_juicer/core/data/load_strategy.py
data_juicer/core/data/ray_dataset.py
data_juicer/core/data/schema.py
data_juicer/core/executor/__init__.py
data_juicer/core/executor/base.py
data_juicer/core/executor/default_executor.py
data_juicer/core/executor/factory.py
data_juicer/core/executor/ray_executor.py
data_juicer/download/__init__.py
data_juicer/download/arxiv.py
data_juicer/download/commoncrawl.py
data_juicer/download/downloader.py
data_juicer/download/wikipedia.py
data_juicer/format/__init__.py
data_juicer/format/csv_formatter.py
data_juicer/format/empty_formatter.py
data_juicer/format/formatter.py
data_juicer/format/json_formatter.py
data_juicer/format/load.py
data_juicer/format/parquet_formatter.py
data_juicer/format/text_formatter.py
data_juicer/format/tsv_formatter.py
data_juicer/ops/__init__.py
data_juicer/ops/base_op.py
data_juicer/ops/load.py
data_juicer/ops/mixins.py
data_juicer/ops/op_fusion.py
data_juicer/ops/aggregator/__init__.py
data_juicer/ops/aggregator/entity_attribute_aggregator.py
data_juicer/ops/aggregator/meta_tags_aggregator.py
data_juicer/ops/aggregator/most_relevant_entities_aggregator.py
py_data_juicer-1.4.5.dist-info/METADATA
py_data_juicer-1.4.5.dist-info/WHEEL
py_data_juicer-1.4.5.dist-info/entry_points.txt
py_data_juicer-1.4.5.dist-info/licenses/LICENSE
py_data_juicer-1.4.5.dist-info/RECORD
