Metadata-Version: 2.4
Name: py-data-juicer
Version: 1.4.5
Summary: Data Processing for and with Foundation Models.
Project-URL: repository, https://github.com/datajuicer/data-juicer
Author: SysML Team of Alibaba Tongyi Lab
License: Apache-2.0
License-File: LICENSE
Classifier: License :: OSI Approved :: Apache Software License
Classifier: Operating System :: OS Independent
Classifier: Programming Language :: Python :: 3
Requires-Python: >=3.10
Requires-Dist: av==13.1.0
Requires-Dist: boto3
Requires-Dist: bs4
Requires-Dist: datasets>=2.19.0
Requires-Dist: dill==0.3.8
Requires-Dist: emoji==2.2.0
Requires-Dist: fastapi>=0.110
Requires-Dist: fsspec==2023.5.0
Requires-Dist: gitpython
Requires-Dist: httpx
Requires-Dist: jsonargparse[signatures]
Requires-Dist: jsonlines
Requires-Dist: librosa>=0.10
Requires-Dist: loguru
Requires-Dist: lz4
Requires-Dist: matplotlib
Requires-Dist: mcp[cli]>=1.7.0
Requires-Dist: multiprocess==0.70.16
Requires-Dist: mwparserfromhell
Requires-Dist: numpy<2.0.0,>=1.26.4
Requires-Dist: pandas
Requires-Dist: pdfplumber
Requires-Dist: pillow
Requires-Dist: plotly
Requires-Dist: psutil
Requires-Dist: pydantic>=2.0
Requires-Dist: pylance
Requires-Dist: python-docx
Requires-Dist: regex
Requires-Dist: requests
Requires-Dist: resampy
Requires-Dist: samplerate==0.1.0
Requires-Dist: seaborn
Requires-Dist: spacy==3.8.7
Requires-Dist: streamlit
Requires-Dist: tabulate
Requires-Dist: tomli
Requires-Dist: tomli-w
Requires-Dist: tqdm
Requires-Dist: uv
Requires-Dist: wget
Requires-Dist: wordcloud==1.9.4
Requires-Dist: zstandard
Provides-Extra: ai-services
Requires-Dist: dashscope; extra == 'ai-services'
Requires-Dist: label-studio==1.17.0; extra == 'ai-services'
Requires-Dist: openai; extra == 'ai-services'
Provides-Extra: all
Requires-Dist: accelerate; extra == 'all'
Requires-Dist: audiomentations; extra == 'all'
Requires-Dist: bitarray; extra == 'all'
Requires-Dist: black>=25.1.0; extra == 'all'
Requires-Dist: build; extra == 'all'
Requires-Dist: click; extra == 'all'
Requires-Dist: coverage; extra == 'all'
Requires-Dist: cudf-cu12==25.4.0; extra == 'all'
Requires-Dist: dashscope; extra == 'all'
Requires-Dist: decord; extra == 'all'
Requires-Dist: diffusers>=0.33.0; extra == 'all'
Requires-Dist: docstring-parser>=0.16; extra == 'all'
Requires-Dist: easyocr==1.7.1; extra == 'all'
Requires-Dist: einops; extra == 'all'
Requires-Dist: fasttext-wheel; extra == 'all'
Requires-Dist: ffmpeg-python; extra == 'all'
Requires-Dist: fire; extra == 'all'
Requires-Dist: flake8-black; extra == 'all'
Requires-Dist: ftfy; extra == 'all'
Requires-Dist: furo; extra == 'all'
Requires-Dist: imagededup; extra == 'all'
Requires-Dist: kenlm; extra == 'all'
Requires-Dist: label-studio==1.17.0; extra == 'all'
Requires-Dist: linkify-it-py; extra == 'all'
Requires-Dist: myst-parser; extra == 'all'
Requires-Dist: nlpaug; extra == 'all'
Requires-Dist: nlpcda; extra == 'all'
Requires-Dist: nltk==3.9.1; extra == 'all'
Requires-Dist: onnxruntime; extra == 'all'
Requires-Dist: openai; extra == 'all'
Requires-Dist: opencc==1.1.9; extra == 'all'
Requires-Dist: opencv-python; extra == 'all'
Requires-Dist: pre-commit; extra == 'all'
Requires-Dist: ptlflow==0.4.1; extra == 'all'
Requires-Dist: pyspark==3.5.5; extra == 'all'
Requires-Dist: pytest; extra == 'all'
Requires-Dist: pytest-cov; extra == 'all'
Requires-Dist: qwen-vl-utils==0.0.14; extra == 'all'
Requires-Dist: ray[default]>=2.51.0; extra == 'all'
Requires-Dist: recommonmark; extra == 'all'
Requires-Dist: rembg; extra == 'all'
Requires-Dist: rouge; extra == 'all'
Requires-Dist: s3fs; extra == 'all'
Requires-Dist: scenedetect[opencv]; extra == 'all'
Requires-Dist: selectolax; extra == 'all'
Requires-Dist: sentencepiece; extra == 'all'
Requires-Dist: simhash-pybind; extra == 'all'
Requires-Dist: simple-aesthetics-predictor; extra == 'all'
Requires-Dist: soundfile; extra == 'all'
Requires-Dist: spacy-pkuseg; extra == 'all'
Requires-Dist: sphinx; extra == 'all'
Requires-Dist: sphinx-autobuild; extra == 'all'
Requires-Dist: sphinx-copybutton; extra == 'all'
Requires-Dist: tiktoken; extra == 'all'
Requires-Dist: timm==1.0.22; extra == 'all'
Requires-Dist: toml; extra == 'all'
Requires-Dist: torch==2.8.0; extra == 'all'
Requires-Dist: torchaudio; extra == 'all'
Requires-Dist: torchcodec==0.7; extra == 'all'
Requires-Dist: transformers==4.57.1; extra == 'all'
Requires-Dist: ultralytics; extra == 'all'
Requires-Dist: uvloop==0.21.0; extra == 'all'
Requires-Dist: vllm==0.11.0; extra == 'all'
Requires-Dist: wandb<=0.19.0; extra == 'all'
Provides-Extra: audio
Requires-Dist: audiomentations; extra == 'audio'
Requires-Dist: ffmpeg-python; extra == 'audio'
Requires-Dist: soundfile; extra == 'audio'
Requires-Dist: torchaudio; extra == 'audio'
Requires-Dist: torchcodec==0.7; extra == 'audio'
Provides-Extra: dev
Requires-Dist: black>=25.1.0; extra == 'dev'
Requires-Dist: build; extra == 'dev'
Requires-Dist: click; extra == 'dev'
Requires-Dist: coverage; extra == 'dev'
Requires-Dist: docstring-parser>=0.16; extra == 'dev'
Requires-Dist: fire; extra == 'dev'
Requires-Dist: flake8-black; extra == 'dev'
Requires-Dist: furo; extra == 'dev'
Requires-Dist: linkify-it-py; extra == 'dev'
Requires-Dist: myst-parser; extra == 'dev'
Requires-Dist: pre-commit; extra == 'dev'
Requires-Dist: pytest; extra == 'dev'
Requires-Dist: pytest-cov; extra == 'dev'
Requires-Dist: recommonmark; extra == 'dev'
Requires-Dist: sphinx; extra == 'dev'
Requires-Dist: sphinx-autobuild; extra == 'dev'
Requires-Dist: sphinx-copybutton; extra == 'dev'
Requires-Dist: toml; extra == 'dev'
Requires-Dist: wandb<=0.19.0; extra == 'dev'
Provides-Extra: distributed
Requires-Dist: bitarray; extra == 'distributed'
Requires-Dist: pyspark==3.5.5; extra == 'distributed'
Requires-Dist: ray[default]>=2.51.0; extra == 'distributed'
Requires-Dist: s3fs; extra == 'distributed'
Requires-Dist: uvloop==0.21.0; extra == 'distributed'
Provides-Extra: generic
Requires-Dist: accelerate; extra == 'generic'
Requires-Dist: cudf-cu12==25.4.0; extra == 'generic'
Requires-Dist: einops; extra == 'generic'
Requires-Dist: onnxruntime; extra == 'generic'
Requires-Dist: torch==2.8.0; extra == 'generic'
Requires-Dist: transformers==4.57.1; extra == 'generic'
Requires-Dist: uvloop==0.21.0; extra == 'generic'
Requires-Dist: vllm==0.11.0; extra == 'generic'
Provides-Extra: nlp
Requires-Dist: easyocr==1.7.1; extra == 'nlp'
Requires-Dist: fasttext-wheel; extra == 'nlp'
Requires-Dist: ftfy; extra == 'nlp'
Requires-Dist: kenlm; extra == 'nlp'
Requires-Dist: nlpaug; extra == 'nlp'
Requires-Dist: nlpcda; extra == 'nlp'
Requires-Dist: nltk==3.9.1; extra == 'nlp'
Requires-Dist: opencc==1.1.9; extra == 'nlp'
Requires-Dist: rouge; extra == 'nlp'
Requires-Dist: selectolax; extra == 'nlp'
Requires-Dist: sentencepiece; extra == 'nlp'
Requires-Dist: simhash-pybind; extra == 'nlp'
Requires-Dist: spacy-pkuseg; extra == 'nlp'
Requires-Dist: tiktoken; extra == 'nlp'
Provides-Extra: vision
Requires-Dist: decord; extra == 'vision'
Requires-Dist: diffusers>=0.33.0; extra == 'vision'
Requires-Dist: imagededup; extra == 'vision'
Requires-Dist: opencv-python; extra == 'vision'
Requires-Dist: ptlflow==0.4.1; extra == 'vision'
Requires-Dist: qwen-vl-utils==0.0.14; extra == 'vision'
Requires-Dist: rembg; extra == 'vision'
Requires-Dist: scenedetect[opencv]; extra == 'vision'
Requires-Dist: simple-aesthetics-predictor; extra == 'vision'
Requires-Dist: timm==1.0.22; extra == 'vision'
Requires-Dist: ultralytics; extra == 'vision'
